dv2s/__init__.py
dv2s/__main__.py
dv2s/classes.py
dv2s/dv2s.py
dv2s/dv2s_gradio.py
dv2s/global_vars.py
dv2s/utils.py
dv2s-0.9.0.dist-info/METADATA
dv2s-0.9.0.dist-info/WHEEL
dv2s-0.9.0.dist-info/licenses/LICENSE
dv2s-0.9.0.dist-info/RECORD
