Metadata-Version: 2.4
Name: dv2s
Version: 0.9.0
Summary: DNA Variance to Structure
Author-email: Ping Wu <wpwupingwp@outlook.com>, Linchuan Deng <linchuan.deng@outlook.com>
License: AGPL-3.0
License-File: LICENSE
Requires-Python: >=3.12
Requires-Dist: biopython>=1.85
Requires-Dist: loguru>=0.7.3
Requires-Dist: matplotlib>=3.10.5
Requires-Dist: requests>=2.32.4
